tcqi/__init__.py
tcqi/main.py
tcqi-0.3.0.dist-info/LICENSE
tcqi-0.3.0.dist-info/METADATA
tcqi-0.3.0.dist-info/WHEEL
tcqi-0.3.0.dist-info/top_level.txt
tcqi-0.3.0.dist-info/RECORD
