Metadata-Version: 2.1
Name: tcqi
Version: 0.3.0
Summary: Intended to facilitate the modification of TCQi files
Author: Sebastián Christen
Author-email: schristen@itec.cat
License: CC-BY-NC-ND
Classifier: Programming Language :: Python :: 3
Classifier: Operating System :: OS Independent
License-File: LICENSE
Requires-Dist: numpy >=2.2.0
Requires-Dist: openpyxl >=3.1.3
Requires-Dist: pandas >=2.2.3
Requires-Dist: plotly >=6.1.0
Requires-Dist: pyodbc >=5.2.0
Requires-Dist: tabulate >=0.9.0
Requires-Dist: xlsxwriter >=3.2.5
